adhs/__init__.py
adhs/_adhs.py
adhs/_alpha.py
adhs/_criterion.py
adhs/_cross_val_shrinkage.py
adhs/_impurity.py
adhs/_util.py
adhs-0.1.3.dist-info/LICENSE
adhs-0.1.3.dist-info/METADATA
adhs-0.1.3.dist-info/WHEEL
adhs-0.1.3.dist-info/top_level.txt
adhs-0.1.3.dist-info/RECORD
