Metadata-Version: 2.1
Name: adhs
Version: 0.1.3
Summary: Adaptive Hierarchical Shrinkage
Author: Markus Loecher, Bastian Pfeifer
Author-email: Arne Gevaert <arne.gevaert@ugent.be>
License: MIT License
Project-URL: Homepage, https://github.com/arnegevaert/adaptive-hierarchical-shrinkage
Classifier: Development Status :: 3 - Alpha
Classifier: License :: OSI Approved :: MIT License
Classifier: Programming Language :: Python
Classifier: Programming Language :: Python :: 3.10
Requires-Python: >=3.8
License-File: LICENSE
Requires-Dist: numpy >=1.23.0
Requires-Dist: scipy >=1.10.0
Requires-Dist: pandas >=1.5.0
Requires-Dist: scikit-learn >=1.2.1
Provides-Extra: dev
Requires-Dist: bumpver ; extra == 'dev'
Provides-Extra: experiments
Requires-Dist: matplotlib ; extra == 'experiments'
Requires-Dist: seaborn ; extra == 'experiments'
Requires-Dist: tqdm ; extra == 'experiments'
Requires-Dist: ipykernel ; extra == 'experiments'
Requires-Dist: imodels ; extra == 'experiments'
Requires-Dist: pmlb ; extra == 'experiments'
Requires-Dist: shap >=0.42.0 ; extra == 'experiments'
